moneymanagerexlib/__init__.py
moneymanagerexlib/command.py
moneymanagerexlib/config.py
moneymanagerexlib/csv.py
moneymanagerexlib/dal.py
moneymanagerexlib/query.py
pymoneymanagerdal/__init__.py
pymoneymanagerdal/dal.py
moneymanagerexlib-1.0.0.dist-info/LICENSE
moneymanagerexlib-1.0.0.dist-info/METADATA
moneymanagerexlib-1.0.0.dist-info/WHEEL
moneymanagerexlib-1.0.0.dist-info/top_level.txt
moneymanagerexlib-1.0.0.dist-info/RECORD
