Metadata-Version: 2.1
Name: moneymanagerexlib
Version: 1.0.0
Summary: Money Manager Ex data access layer
Home-page: https://gitlab.com/alensiljak/moneymanagerexlib
Author: Alen Siljak
Author-email: alen.siljak@gmx.com
License: GPL version 3
Requires-Dist: sqlalchemy
